laser_egismos.py
circuitpython_laser_egismos-1.2.0.dist-info/LICENSE
circuitpython_laser_egismos-1.2.0.dist-info/METADATA
circuitpython_laser_egismos-1.2.0.dist-info/WHEEL
circuitpython_laser_egismos-1.2.0.dist-info/top_level.txt
circuitpython_laser_egismos-1.2.0.dist-info/RECORD
