Metadata-Version: 2.1
Name: circuitpython-laser-egismos
Version: 1.2.0
Summary: Device driver for the egismos series of lasers, available at https://www.egismos.com/laser-measuring-optoelectronics-module
Author-email: Adafruit Industries <circuitpython@adafruit.com>
License: MIT
Project-URL: Homepage, https://github.com/furbrain/CircuitPython_laser_egismos
Keywords: adafruit,blinka,circuitpython,micropython,laser_egismos,laser,egismos,rangefinder,distance
Classifier: Intended Audience :: Developers
Classifier: Topic :: Software Development :: Libraries
Classifier: Topic :: Software Development :: Embedded Systems
Classifier: Topic :: System :: Hardware
Classifier: License :: OSI Approved :: MIT License
Classifier: Programming Language :: Python :: 3
License-File: LICENSE
Requires-Dist: Adafruit-Blinka
Provides-Extra: optional
